meddlr/__init__.py
meddlr/checkpoint/__init__.py
meddlr/checkpoint/checkpoint.py
meddlr/config/__init__.py
meddlr/config/compat.py
meddlr/config/config.py
meddlr/config/defaults.py
meddlr/config/util.py
meddlr/data/__init__.py
meddlr/data/build.py
meddlr/data/catalog.py
meddlr/data/collate.py
meddlr/data/data_utils.py
meddlr/data/slice_dataset.py
meddlr/data/datasets/__init__.py
meddlr/data/datasets/builtin.py
meddlr/data/datasets/register_mrco.py
meddlr/data/samplers/__init__.py
meddlr/data/samplers/build.py
meddlr/data/samplers/group_sampler.py
meddlr/data/samplers/sampler.py
meddlr/data/transforms/__init__.py
meddlr/data/transforms/motion.py
meddlr/data/transforms/noise.py
meddlr/data/transforms/noiseandmotion.py
meddlr/data/transforms/subsample.py
meddlr/data/transforms/transform.py
meddlr/engine/__init__.py
meddlr/engine/defaults.py
meddlr/engine/hooks.py
meddlr/engine/model_zoo.py
meddlr/engine/sharing.py
meddlr/engine/train_loop.py
meddlr/engine/trainer.py
meddlr/evaluation/__init__.py
meddlr/evaluation/evaluator.py
meddlr/evaluation/recon_evaluation.py
meddlr/evaluation/scan_evaluator.py
meddlr/evaluation/seg_evaluation.py
meddlr/evaluation/testing.py
meddlr/forward/__init__.py
meddlr/forward/mri.py
meddlr/metrics/__init__.py
meddlr/metrics/build.py
meddlr/metrics/collection.py
meddlr/metrics/image.py
meddlr/metrics/lpip.py
meddlr/metrics/metric.py
meddlr/metrics/sem_seg.py
meddlr/metrics/ssfd.py
meddlr/metrics/functional/__init__.py
meddlr/metrics/functional/image.py
meddlr/metrics/functional/sem_seg.py
meddlr/metrics/functional/util.py
meddlr/modeling/__init__.py
meddlr/modeling/loss_computer.py
meddlr/modeling/blocks/__init__.py
meddlr/modeling/blocks/conv_blocks.py
meddlr/modeling/blocks/fuse_blocks.py
meddlr/modeling/layers/__init__.py
meddlr/modeling/layers/build.py
meddlr/modeling/layers/conv.py
meddlr/modeling/layers/gauss.py
meddlr/modeling/layers/layers2D.py
meddlr/modeling/layers/layers3D.py
meddlr/modeling/layers/scale.py
meddlr-0.0.9.dist-info/LICENSE
meddlr-0.0.9.dist-info/METADATA
meddlr-0.0.9.dist-info/WHEEL
meddlr-0.0.9.dist-info/top_level.txt
meddlr-0.0.9.dist-info/RECORD
