Metadata-Version: 2.1
Name: meddlr
Version: 0.0.9
Summary: Meddlr is a config-driven framework built to simplify ML-based medical image reconstruction and analysis.
Home-page: https://github.com/ad12/meddlr
Author: The Meddlr Team
Author-email: arjundd@stanford.edu
Classifier: Programming Language :: Python :: 3
Classifier: Operating System :: OS Independent
Classifier: Topic :: Scientific/Engineering :: Artificial Intelligence
Requires-Python: >=3.6
License-File: LICENSE
Requires-Dist: pyxb
Requires-Dist: h5py
Requires-Dist: matplotlib
Requires-Dist: numpy (<=1.23.5)
Requires-Dist: tensorboard
Requires-Dist: fvcore
Requires-Dist: mridata
Requires-Dist: scikit-image (>=0.18.2)
Requires-Dist: sigpy (>=0.1.17)
Requires-Dist: ismrmrd
Requires-Dist: pandas
Requires-Dist: silx
Requires-Dist: tqdm
Requires-Dist: omegaconf
Requires-Dist: torchmetrics (<=0.11.4,>=0.5.1)
Requires-Dist: iopath
Requires-Dist: packaging
Provides-Extra: all
Requires-Dist: medpy ; extra == 'all'
Requires-Dist: iocursor ; extra == 'all'
Requires-Dist: requests ; extra == 'all'
Requires-Dist: monai ; extra == 'all'
Requires-Dist: gdown (<4.6.0) ; extra == 'all'
Requires-Dist: lpips ; extra == 'all'
Provides-Extra: alldev
Requires-Dist: sphinx-rtd-theme ; extra == 'alldev'
Requires-Dist: flake8 ; extra == 'alldev'
Requires-Dist: monai ; extra == 'alldev'
Requires-Dist: pooch ; extra == 'alldev'
Requires-Dist: pytest ; extra == 'alldev'
Requires-Dist: medpy ; extra == 'alldev'
Requires-Dist: tifffile (<=2022.5.4) ; extra == 'alldev'
Requires-Dist: sphinxcontrib-bibtex ; extra == 'alldev'
Requires-Dist: sphinx ; extra == 'alldev'
Requires-Dist: wrapt ; extra == 'alldev'
Requires-Dist: requests ; extra == 'alldev'
Requires-Dist: black (==22.12.0) ; extra == 'alldev'
Requires-Dist: parameterized ; extra == 'alldev'
Requires-Dist: flake8-comprehensions ; extra == 'alldev'
Requires-Dist: flake8-bugbear ; extra == 'alldev'
Requires-Dist: iocursor ; extra == 'alldev'
Requires-Dist: m2r2 ; extra == 'alldev'
Requires-Dist: sphinxcontrib.bibtex ; extra == 'alldev'
Requires-Dist: pre-commit (>=2.9.3) ; extra == 'alldev'
Requires-Dist: gdown (<4.6.0) ; extra == 'alldev'
Requires-Dist: coverage ; extra == 'alldev'
Requires-Dist: lpips ; extra == 'alldev'
Requires-Dist: isort ; extra == 'alldev'
Provides-Extra: benchmarking
Requires-Dist: medpy ; extra == 'benchmarking'
Provides-Extra: deployment
Requires-Dist: gdown (<4.6.0) ; extra == 'deployment'
Requires-Dist: requests ; extra == 'deployment'
Requires-Dist: iocursor ; extra == 'deployment'
Provides-Extra: dev
Requires-Dist: coverage ; extra == 'dev'
Requires-Dist: flake8 ; extra == 'dev'
Requires-Dist: isort ; extra == 'dev'
Requires-Dist: black (==22.12.0) ; extra == 'dev'
Requires-Dist: flake8-bugbear ; extra == 'dev'
Requires-Dist: flake8-comprehensions ; extra == 'dev'
Requires-Dist: pre-commit (>=2.9.3) ; extra == 'dev'
Requires-Dist: pytest ; extra == 'dev'
Requires-Dist: medpy ; extra == 'dev'
Requires-Dist: wrapt ; extra == 'dev'
Requires-Dist: pooch ; extra == 'dev'
Requires-Dist: gdown (<4.6.0) ; extra == 'dev'
Requires-Dist: parameterized ; extra == 'dev'
Requires-Dist: tifffile (<=2022.5.4) ; extra == 'dev'
Requires-Dist: sphinx ; extra == 'dev'
Requires-Dist: sphinxcontrib-bibtex ; extra == 'dev'
Requires-Dist: sphinx-rtd-theme ; extra == 'dev'
Requires-Dist: m2r2 ; extra == 'dev'
Provides-Extra: docs
Requires-Dist: sphinx ; extra == 'docs'
Requires-Dist: sphinxcontrib.bibtex ; extra == 'docs'
Requires-Dist: sphinx-rtd-theme ; extra == 'docs'
Requires-Dist: m2r2 ; extra == 'docs'
Provides-Extra: metrics
Requires-Dist: lpips ; extra == 'metrics'
Provides-Extra: modeling
Requires-Dist: monai ; extra == 'modeling'
